{"cameraMode":{"drawMode":0,"name":"Shaded","section":"Shading Mode"},"sceneLighting":false,"audioPlay":false,"sceneViewState":{"m_AlwaysRefresh":false,"showFog":true,"showSkybox":false,"showFlares":true,"showImageEffects":true,"showParticleSystems":true,"showVisualEffectGraphs":true,"m_FxEnabled":true},"in2DMode":false,"pivot":{"x":42.29978942871094,"y":6.474999904632568,"z":47.40999984741211},"rotation":{"x":-0.26078978180885317,"y":-0.7199159860610962,"z":0.3464275598526001,"w":-0.5419474840164185},"size":6.411220550537109,"orthographic":false}